crewai_ui/__init__.py
crewai_ui/app/__init__.py
crewai_ui/app/app.py
crewai_ui/app/static/dist/css/output.css
crewai_ui/app/static/src/input.css
crewai_ui/app/tailwind.config.js
crewai_ui/app/templates/index.html
crewai_ui/cli.py
crewai_ui-0.1.0.dist-info/METADATA
crewai_ui-0.1.0.dist-info/WHEEL
crewai_ui-0.1.0.dist-info/entry_points.txt
crewai_ui-0.1.0.dist-info/RECORD
