Metadata-Version: 2.1
Name: crewai-ui
Version: 0.1.0
Summary: 
Author: João Moura
Author-email: joaomdmoura@mgail.com
Requires-Python: >=3.11,<4.0
Classifier: Programming Language :: Python :: 3
Classifier: Programming Language :: Python :: 3.11
Classifier: Programming Language :: Python :: 3.12
Requires-Dist: click (>=8.1.7,<9.0.0)
Requires-Dist: flask (>=3.0.0,<4.0.0)
